prerun/__init__.py
prerun/__main__.py
prerun/client.py
prerun/recv_bytes.py
prerun/server.py
prerun/sigint.py
prerun-1.1.3.dist-info/LICENSE
prerun-1.1.3.dist-info/METADATA
prerun-1.1.3.dist-info/WHEEL
prerun-1.1.3.dist-info/entry_points.txt
prerun-1.1.3.dist-info/top_level.txt
prerun-1.1.3.dist-info/RECORD
