Metadata-Version: 2.1
Name: prerun
Version: 1.1.3
Summary: Prerun
License: Copyright (c) <year> <copyright holders>
Project-URL: Homepage, https://github.com/sfanxiang/prerun
Keywords: development
Classifier: Development Status :: 3 - Alpha
Classifier: Intended Audience :: Developers
Classifier: License :: OSI Approved :: MIT License
Requires-Python: >=3.9
License-File: LICENSE
Requires-Dist: psutil >=5.9.0
